to_json_schema/__init__.py
to_json_schema/combine.py
to_json_schema/constants.py
to_json_schema/to_json_schema.py
to_json_schema/utils.py
to_json_schema-1.0.1.dist-info/LICENSE.txt
to_json_schema-1.0.1.dist-info/METADATA
to_json_schema-1.0.1.dist-info/WHEEL
to_json_schema-1.0.1.dist-info/top_level.txt
to_json_schema-1.0.1.dist-info/RECORD
