Metadata-Version: 2.1
Name: to-json-schema
Version: 1.0.1
Home-page: https://github.com/zilehuda/to-json-schema/
Author: zilehuda
Author-email: 
License: MIT
Project-URL: Source, https://github.com/zilehuda/to-json-schema/
Project-URL: Tracker, https://github.com/zilehuda/to-json-schema/issues
Platform: any
Classifier: Development Status :: 4 - Beta
Classifier: Programming Language :: Python
License-File: LICENSE.txt
Requires-Dist: importlib-metadata ; python_version < "3.8"
Provides-Extra: testing
Requires-Dist: setuptools ; extra == 'testing'
Requires-Dist: pytest ; extra == 'testing'
Requires-Dist: pytest-cov ; extra == 'testing'
